rv_helpers/__init__.py
rv_helpers/byte_chapters.py
rv_helpers/zb_app.py
rv_helpers/data/__init__.py
rv_helpers/data/byte_chapters/__init__.py
rv_helpers/data/byte_chapters/data.py
rv_helpers/data/zb_vstore/default__vector_store.json
rv_helpers/data/zb_vstore/docstore.json
rv_helpers/data/zb_vstore/graph_store.json
rv_helpers/data/zb_vstore/image__vector_store.json
rv_helpers/data/zb_vstore/index_store.json
rv_helpers-0.1.dist-info/METADATA
rv_helpers-0.1.dist-info/WHEEL
rv_helpers-0.1.dist-info/top_level.txt
rv_helpers-0.1.dist-info/RECORD
