Metadata-Version: 2.1
Name: rv-helpers
Version: 0.1
Summary: rv_helpers package
Home-page: UNKNOWN
Author: Robert
Author-email: robert.valassi@accenture.com
License: MIT
Platform: UNKNOWN
Requires-Python: >=3.7
